cs/__init__.py
cs/cli.py
cs/data/.gitkeep
cs/data/data.csv
cs/db.py
cs/output.py
cs/policy_reader.py
cs/relevance.py
cs/utils.py
climate_search_cli-0.1.4.dist-info/LICENSE
climate_search_cli-0.1.4.dist-info/WHEEL
climate_search_cli-0.1.4.dist-info/entry_points.txt
climate_search_cli-0.1.4.dist-info/METADATA
climate_search_cli-0.1.4.dist-info/RECORD
