Metadata-Version: 2.1
Name: climate-search-cli
Version: 0.1.4
Summary: A python program that can be run from the command line, and used to search climate policy documents.
License: Apache-2.0
Author: fred oloughlin
Author-email: fred@oloughl.in
Requires-Python: >=3.10,<4.0
Classifier: License :: OSI Approved :: Apache Software License
Classifier: Programming Language :: Python :: 3
Classifier: Programming Language :: Python :: 3.10
Classifier: Programming Language :: Python :: 3.11
Requires-Dist: click (>=8.1.6,<9.0.0)
Requires-Dist: numpy (==1.24.4)
Requires-Dist: pandas (>=2.0.3,<3.0.0)
Requires-Dist: scikit-learn (>=1.3.0,<2.0.0)
Requires-Dist: sqlalchemy (>=2.0.19,<3.0.0)
